<font>
	<info face="number_dragon_round" size="72" />
	<common lineHeight="72" scaleW="218" scaleH="218" pages="1" />
	<pages>
		<page id="0" file="number_dragon_round.png" />
	</pages>
	<chars count="14">
		<char id="48" x="110" y="72" width="52" height="71" xoffset="0" yoffset="1" xadvance="57" /><!-- 0 -->
		<char id="49" x="111" y="0" width="38" height="69" xoffset="0" yoffset="2" xadvance="43" /><!-- 1 -->
		<char id="50" x="56" y="0" width="53" height="70" xoffset="0" yoffset="1" xadvance="58" /><!-- 2 -->
		<char id="51" x="0" y="0" width="54" height="71" xoffset="0" yoffset="1" xadvance="59" /><!-- 3 -->
		<char id="52" x="0" y="73" width="54" height="69" xoffset="0" yoffset="2" xadvance="59" /><!-- 4 -->
		<char id="53" x="56" y="72" width="52" height="70" xoffset="0" yoffset="2" xadvance="57" /><!-- 5 -->
		<char id="54" x="0" y="144" width="53" height="71" xoffset="0" yoffset="1" xadvance="58" /><!-- 6 -->
		<char id="55" x="55" y="144" width="53" height="69" xoffset="0" yoffset="2" xadvance="58" /><!-- 7 -->
		<char id="56" x="110" y="145" width="52" height="71" xoffset="0" yoffset="1" xadvance="57" /><!-- 8 -->
		<char id="57" x="164" y="0" width="52" height="71" xoffset="0" yoffset="1" xadvance="57" /><!-- 9 -->
		<char id="44" x="164" y="98" width="26" height="36" xoffset="0" yoffset="51" xadvance="31" /><!-- , -->
		<char id="46" x="164" y="73" width="26" height="23" xoffset="0" yoffset="48" xadvance="31" /><!-- . -->
		<char id="32" x="0" y="0" width="0" height="0" xoffset="0" yoffset="0" xadvance="32" /><!--   -->
		<char id="9" x="0" y="0" width="0" height="0" xoffset="0" yoffset="0" xadvance="256" /><!-- 	 -->
	</chars>
	<kernings count="0">
	</kernings>
</font>